sweeps/__init__.py
sweeps/_types.py
sweeps/bayes_search.py
sweeps/grid_search.py
sweeps/hyperband_stopping.py
sweeps/params.py
sweeps/random_search.py
sweeps/run.py
sweeps/config/__init__.py
sweeps/config/cfg.py
sweeps/config/schema.json
sweeps/config/schema.py
sweeps-0.2.0.dist-info/LICENSE
sweeps-0.2.0.dist-info/METADATA
sweeps-0.2.0.dist-info/WHEEL
sweeps-0.2.0.dist-info/top_level.txt
sweeps-0.2.0.dist-info/RECORD
