Metadata-Version: 2.1
Name: sweeps
Version: 0.2.0
Summary: Weights and Biases Hyperparameter Sweeps Engine.
Home-page: https://github.com/wandb/sweeps
Author: Weights & Biases
Author-email: support@wandb.com
License: MIT license
Platform: UNKNOWN
Classifier: Development Status :: 5 - Production/Stable
Classifier: Intended Audience :: Developers
Classifier: Intended Audience :: Science/Research
Classifier: License :: OSI Approved :: MIT License
Classifier: Natural Language :: English
Classifier: Programming Language :: Python :: 3
Classifier: Programming Language :: Python :: 3.6
Classifier: Programming Language :: Python :: 3.7
Classifier: Programming Language :: Python :: 3.8
Classifier: Programming Language :: Python :: 3.9
Classifier: Programming Language :: Python :: 3.10
Classifier: Topic :: Scientific/Engineering :: Artificial Intelligence
Classifier: Topic :: Software Development :: Libraries :: Python Modules
Requires-Python: >=3.6
License-File: LICENSE
Requires-Dist: numpy (>=1.15)
Requires-Dist: scipy (>=1.5.4)
Requires-Dist: PyYAML
Requires-Dist: jsonschema (>=3.2.0)
Requires-Dist: jsonref (>=0.2)
Requires-Dist: pydantic (>=1.8.2)
Requires-Dist: scikit-learn (>=0.24.2) ; python_version == "3.6"
Requires-Dist: scikit-learn (>=1.0) ; python_version > "3.6"
